ticktocker/__init__.py
ticktocker/stopwatch.py
ticktocker/utils.py
ticktocker-0.7.dist-info/licenses/LICENSE
ticktocker-0.7.dist-info/METADATA
ticktocker-0.7.dist-info/WHEEL
ticktocker-0.7.dist-info/top_level.txt
ticktocker-0.7.dist-info/RECORD
