Metadata-Version: 2.4
Name: ticktocker
Version: 0.7
Summary: A simple Python package for clocking
Author-email: Yeho Gwon <yeho.gwon@postech.ac.kr>
License: MIT
Requires-Python: >=3.10
License-File: LICENSE
Dynamic: license-file
